LICENSE
emojifs/__init__.py
emojifs/__main__.py
emojifs/constants.py
emojifs/discord.py
emojifs/muxer.py
emojifs/slack.py
emojifs/utils.py
emojifs-0.2.0.dist-info/entry_points.txt
emojifs-0.2.0.dist-info/LICENSE
emojifs-0.2.0.dist-info/WHEEL
emojifs-0.2.0.dist-info/METADATA
emojifs-0.2.0.dist-info/RECORD
