Metadata-Version: 2.1
Name: emojifs
Version: 0.2.0
Summary: A FUSE filesystem to manipulate custom emojis on your various Slacks and Discords
Home-page: https://github.com/cdanis/emojifs
License: GPL-3.0-only
Keywords: fuse,slack,discord,emoji
Author: Chris Danis
Author-email: cdanis@gmail.com
Requires-Python: >=3.7,<4.0
Classifier: Development Status :: 3 - Alpha
Classifier: Environment :: No Input/Output (Daemon)
Classifier: License :: OSI Approved :: GNU General Public License v3 (GPLv3)
Classifier: Programming Language :: Python :: 3
Classifier: Programming Language :: Python :: 3.7
Classifier: Programming Language :: Python :: 3.8
Classifier: Topic :: Communications
Classifier: Topic :: System :: Filesystems
Requires-Dist: cachetools (>=4,<5)
Requires-Dist: logzero (>=1.5.0,<2.0.0)
Requires-Dist: refuse (>=0,<1)
Requires-Dist: requests (>=2,<3)
Requires-Dist: tomlkit (>=0.6.0,<0.7.0)
Project-URL: Repository, https://github.com/cdanis/emojifs
